simplerag/__init__.py
simplerag/db_creation.py
simplerag/load_model.py
simplerag/prompts.py
simplerag/rag_inferencing.py
simplerag-0.0.4.dist-info/METADATA
simplerag-0.0.4.dist-info/WHEEL
simplerag-0.0.4.dist-info/top_level.txt
simplerag-0.0.4.dist-info/RECORD
